README.md
setup.py
bridgewalk/__init__.py
bridgewalk/bridgewalk.py
bridgewalk/constants.py
bridgewalk/data.yaml
bridgewalk/engine.py
bridgewalk/objects.py
bridgewalk/run_gui.py
bridgewalk/run_random.py
bridgewalk/worldgen.py
bridgewalk.egg-info/PKG-INFO
bridgewalk.egg-info/SOURCES.txt
bridgewalk.egg-info/dependency_links.txt
bridgewalk.egg-info/entry_points.txt
bridgewalk.egg-info/requires.txt
bridgewalk.egg-info/top_level.txt
bridgewalk/assets/arrow-left.png
bridgewalk/assets/bridge.png
bridgewalk/assets/crate.png
bridgewalk/assets/edit_list.tmp
bridgewalk/assets/grass.png
bridgewalk/assets/player-down.png
bridgewalk/assets/player-left.png
bridgewalk/assets/player-right.png
bridgewalk/assets/player-up.png
bridgewalk/assets/player-water.png
bridgewalk/assets/player.png
bridgewalk/assets/sand.png
bridgewalk/assets/tree.png
bridgewalk/assets/unknown.png
bridgewalk/assets/water.png