Metadata-Version: 2.1
Name: bridgewalk
Version: 0.1.0
Summary: Visual reinforcement learning benchmark for controllability.
Home-page: http://github.com/danijar/bridgewalk
License: UNKNOWN
Platform: UNKNOWN
Classifier: Intended Audience :: Science/Research
Classifier: License :: OSI Approved :: MIT License
Classifier: Programming Language :: Python :: 3
Classifier: Topic :: Games/Entertainment
Classifier: Topic :: Scientific/Engineering :: Artificial Intelligence
Provides-Extra: gui
